js2py_/__init__.py
js2py_/base.py
js2py_/evaljs.py
js2py_/node_import.py
js2py_/pyjs.py
js2py_/constructors/__init__.py
js2py_/constructors/jsarray.py
js2py_/constructors/jsarraybuffer.py
js2py_/constructors/jsboolean.py
js2py_/constructors/jsdate.py
js2py_/constructors/jsfloat32array.py
js2py_/constructors/jsfloat64array.py
js2py_/constructors/jsfunction.py
js2py_/constructors/jsint16array.py
js2py_/constructors/jsint32array.py
js2py_/constructors/jsint8array.py
js2py_/constructors/jsmath.py
js2py_/constructors/jsnumber.py
js2py_/constructors/jsobject.py
js2py_/constructors/jsregexp.py
js2py_/constructors/jsstring.py
js2py_/constructors/jsuint16array.py
js2py_/constructors/jsuint32array.py
js2py_/constructors/jsuint8array.py
js2py_/constructors/jsuint8clampedarray.py
js2py_/constructors/time_helpers.py
js2py_/es6/__init__.py
js2py_/es6/babel.py
js2py_/host/__init__.py
js2py_/host/console.py
js2py_/host/jseval.py
js2py_/host/jsfunctions.py
js2py_/internals/__init__.py
js2py_/internals/base.py
js2py_/internals/byte_trans.py
js2py_/internals/code.py
js2py_/internals/conversions.py
js2py_/internals/desc.py
js2py_/internals/fill_space.py
js2py_/internals/func_utils.py
js2py_/internals/gen.py
js2py_/internals/opcodes.py
js2py_/internals/operations.py
js2py_/internals/seval.py
js2py_/internals/simplex.py
js2py_/internals/space.py
js2py_/internals/speed.py
js2py_/internals/trans_utils.py
js2py_/internals/constructors/__init__.py
js2py_/internals/constructors/jsarray.py
js2py_/internals/constructors/jsboolean.py
js2py_/internals/constructors/jsconsole.py
js2py_/internals/constructors/jsdate.py
js2py_/internals/constructors/jsfunction.py
js2py_/internals/constructors/jsmath.py
js2py_/internals/constructors/jsnumber.py
js2py_/internals/constructors/jsobject.py
js2py_/internals/constructors/jsregexp.py
js2py_/internals/constructors/jsstring.py
js2py_/internals/constructors/time_helpers.py
js2py_/internals/prototypes/__init__.py
js2py_/internals/prototypes/jsarray.py
Js2Py_3.13-0.74.dist-info/LICENSE.md
Js2Py_3.13-0.74.dist-info/METADATA
Js2Py_3.13-0.74.dist-info/WHEEL
Js2Py_3.13-0.74.dist-info/top_level.txt
Js2Py_3.13-0.74.dist-info/RECORD
